utstd/__init__.py
utstd/folders.py
utstd/ipyrenders.py
utstd-0.1.7.dist-info/METADATA
utstd-0.1.7.dist-info/WHEEL
utstd-0.1.7.dist-info/entry_points.txt
utstd-0.1.7.dist-info/RECORD
